LICENSE
MANIFEST.in
ecs_composex_msk_cluster/__init__.py
ecs_composex_msk_cluster/msk_cluster.py
ecs_composex_msk_cluster/msk_cluster_conditions.py
ecs_composex_msk_cluster/msk_cluster_ecs.py
ecs_composex_msk_cluster/msk_cluster_ecs_iam.py
ecs_composex_msk_cluster/msk_cluster_logging.py
ecs_composex_msk_cluster/msk_cluster_module.py
ecs_composex_msk_cluster/msk_cluster_params.py
ecs_composex_msk_cluster/msk_cluster_perms.json
ecs_composex_msk_cluster/msk_cluster_stack.py
ecs_composex_msk_cluster/msk_cluster_template.py
ecs_composex_msk_cluster/msk_configuration.py
ecs_composex_msk_cluster/msk_sg_ingress.py
ecs_composex_msk_cluster/msk_storage_scaling.py
ecs_composex_msk_cluster/x-msk_cluster.spec.json
ecs_composex_msk_cluster-1.0.1.dist-info/AUTHORS.rst
ecs_composex_msk_cluster-1.0.1.dist-info/LICENSE
ecs_composex_msk_cluster-1.0.1.dist-info/METADATA
ecs_composex_msk_cluster-1.0.1.dist-info/WHEEL
ecs_composex_msk_cluster-1.0.1.dist-info/RECORD
