Metadata-Version: 2.1
Name: ecs_composex_msk_cluster
Version: 1.0.1
Summary: msk_cluster - AWS MSK Cluster module for ECS Compose-X
License: MPL-2.0
Author: johnpreston
Author-email: john@compose-x.io
Requires-Python: >=3.9,<4.0
Classifier: Development Status :: 4 - Beta
Classifier: Intended Audience :: Developers
Classifier: Intended Audience :: Information Technology
Classifier: Intended Audience :: System Administrators
Classifier: License :: OSI Approved
Classifier: License :: OSI Approved :: Mozilla Public License 2.0 (MPL 2.0)
Classifier: Natural Language :: English
Classifier: Programming Language :: Python :: 3
Classifier: Programming Language :: Python :: 3.9
Classifier: Programming Language :: Python :: 3.10
Classifier: Programming Language :: Python :: 3.11
Classifier: Programming Language :: Python :: 3.12
Classifier: Programming Language :: Python :: 3.8
Requires-Dist: compose-x-common (>=1.1,<2.0)
Requires-Dist: ecs_composex (>=1.1,<2.0)
Project-URL: Compose-X Labs, https://labs.compose-x.io/
Project-URL: Compose-X Blog, https://blog.compose-x.io/
Project-URL: ECS ComposeX, https://github.com/compose-x/ecs_composex/
